{
  "code": 200,
  "status": "OK",
  "data": [
    {
      "number": 43,
      "name": "سورة الزخرف",
      "englishName": "Az-Zukhruf",
      "englishNameTranslation": "Ornaments of gold",
      "revelationType": "Meccan",
      "numberOfAyahs": 89,
      "ayahs": [
        {
          "number": 4326,
          "text": "بِسْمِ ٱللَّهِ ٱلرَّحْمَٰنِ ٱلرَّحِيمِ حمٓ",
          "numberInSurah": 1,
          "juz": 25,
          "manzil": 6,
          "page": 489,
          "ruku": 424,
          "hizbQuarter": 196,
          "sajda": false
        },
        {
          "number": 4327,
          "text": "وَٱلْكِتَٰبِ ٱلْمُبِينِ",
          "numberInSurah": 2,
          "juz": 25,
          "manzil": 6,
          "page": 489,
          "ruku": 424,
          "hizbQuarter": 196,
          "sajda": false
        },
        {
          "number": 4328,
          "text": "إِنَّا جَعَلْنَٰهُ قُرْءَٰنًا عَرَبِيًّۭا لَّعَلَّكُمْ تَعْقِلُونَ",
          "numberInSurah": 3,
          "juz": 25,
          "manzil": 6,
          "page": 489,
          "ruku": 424,
          "hizbQuarter": 196,
          "sajda": false
        },
        {
          "number": 4329,
          "text": "وَإِنَّهُۥ فِىٓ أُمِّ ٱلْكِتَٰبِ لَدَيْنَا لَعَلِىٌّ حَكِيمٌ",
          "numberInSurah": 4,
          "juz": 25,
          "manzil": 6,
          "page": 489,
          "ruku": 424,
          "hizbQuarter": 196,
          "sajda": false
        },
        {
          "number": 4330,
          "text": "أَفَنَضْرِبُ عَنكُمُ ٱلذِّكْرَ صَفْحًا أَن كُنتُمْ قَوْمًۭا مُّسْرِفِينَ",
          "numberInSurah": 5,
          "juz": 25,
          "manzil": 6,
          "page": 489,
          "ruku": 424,
          "hizbQuarter": 196,
          "sajda": false
        },
        {
          "number": 4331,
          "text": "وَكَمْ أَرْسَلْنَا مِن نَّبِىٍّۢ فِى ٱلْأَوَّلِينَ",
          "numberInSurah": 6,
          "juz": 25,
          "manzil": 6,
          "page": 489,
          "ruku": 424,
          "hizbQuarter": 196,
          "sajda": false
        },
        {
          "number": 4332,
          "text": "وَمَا يَأْتِيهِم مِّن نَّبِىٍّ إِلَّا كَانُوا۟ بِهِۦ يَسْتَهْزِءُونَ",
          "numberInSurah": 7,
          "juz": 25,
          "manzil": 6,
          "page": 489,
          "ruku": 424,
          "hizbQuarter": 196,
          "sajda": false
        },
        {
          "number": 4333,
          "text": "فَأَهْلَكْنَآ أَشَدَّ مِنْهُم بَطْشًۭا وَمَضَىٰ مَثَلُ ٱلْأَوَّلِينَ",
          "numberInSurah": 8,
          "juz": 25,
          "manzil": 6,
          "page": 489,
          "ruku": 424,
          "hizbQuarter": 196,
          "sajda": false
        },
        {
          "number": 4334,
          "text": "وَلَئِن سَأَلْتَهُم مَّنْ خَلَقَ ٱلسَّمَٰوَٰتِ وَٱلْأَرْضَ لَيَقُولُنَّ خَلَقَهُنَّ ٱلْعَزِيزُ ٱلْعَلِيمُ",
          "numberInSurah": 9,
          "juz": 25,
          "manzil": 6,
          "page": 489,
          "ruku": 424,
          "hizbQuarter": 196,
          "sajda": false
        },
        {
          "number": 4335,
          "text": "ٱلَّذِى جَعَلَ لَكُمُ ٱلْأَرْضَ مَهْدًۭا وَجَعَلَ لَكُمْ فِيهَا سُبُلًۭا لَّعَلَّكُمْ تَهْتَدُونَ",
          "numberInSurah": 10,
          "juz": 25,
          "manzil": 6,
          "page": 489,
          "ruku": 424,
          "hizbQuarter": 196,
          "sajda": false
        },
        {
          "number": 4336,
          "text": "وَٱلَّذِى نَزَّلَ مِنَ ٱلسَّمَآءِ مَآءًۢ بِقَدَرٍۢ فَأَنشَرْنَا بِهِۦ بَلْدَةًۭ مَّيْتًۭا ۚ كَذَٰلِكَ تُخْرَجُونَ",
          "numberInSurah": 11,
          "juz": 25,
          "manzil": 6,
          "page": 490,
          "ruku": 424,
          "hizbQuarter": 196,
          "sajda": false
        },
        {
          "number": 4337,
          "text": "وَٱلَّذِى خَلَقَ ٱلْأَزْوَٰجَ كُلَّهَا وَجَعَلَ لَكُم مِّنَ ٱلْفُلْكِ وَٱلْأَنْعَٰمِ مَا تَرْكَبُونَ",
          "numberInSurah": 12,
          "juz": 25,
          "manzil": 6,
          "page": 490,
          "ruku": 424,
          "hizbQuarter": 196,
          "sajda": false
        },
        {
          "number": 4338,
          "text": "لِتَسْتَوُۥا۟ عَلَىٰ ظُهُورِهِۦ ثُمَّ تَذْكُرُوا۟ نِعْمَةَ رَبِّكُمْ إِذَا ٱسْتَوَيْتُمْ عَلَيْهِ وَتَقُولُوا۟ سُبْحَٰنَ ٱلَّذِى سَخَّرَ لَنَا هَٰذَا وَمَا كُنَّا لَهُۥ مُقْرِنِينَ",
          "numberInSurah": 13,
          "juz": 25,
          "manzil": 6,
          "page": 490,
          "ruku": 424,
          "hizbQuarter": 196,
          "sajda": false
        },
        {
          "number": 4339,
          "text": "وَإِنَّآ إِلَىٰ رَبِّنَا لَمُنقَلِبُونَ",
          "numberInSurah": 14,
          "juz": 25,
          "manzil": 6,
          "page": 490,
          "ruku": 424,
          "hizbQuarter": 196,
          "sajda": false
        },
        {
          "number": 4340,
          "text": "وَجَعَلُوا۟ لَهُۥ مِنْ عِبَادِهِۦ جُزْءًا ۚ إِنَّ ٱلْإِنسَٰنَ لَكَفُورٌۭ مُّبِينٌ",
          "numberInSurah": 15,
          "juz": 25,
          "manzil": 6,
          "page": 490,
          "ruku": 424,
          "hizbQuarter": 196,
          "sajda": false
        },
        {
          "number": 4341,
          "text": "أَمِ ٱتَّخَذَ مِمَّا يَخْلُقُ بَنَاتٍۢ وَأَصْفَىٰكُم بِٱلْبَنِينَ",
          "numberInSurah": 16,
          "juz": 25,
          "manzil": 6,
          "page": 490,
          "ruku": 425,
          "hizbQuarter": 196,
          "sajda": false
        },
        {
          "number": 4342,
          "text": "وَإِذَا بُشِّرَ أَحَدُهُم بِمَا ضَرَبَ لِلرَّحْمَٰنِ مَثَلًۭا ظَلَّ وَجْهُهُۥ مُسْوَدًّۭا وَهُوَ كَظِيمٌ",
          "numberInSurah": 17,
          "juz": 25,
          "manzil": 6,
          "page": 490,
          "ruku": 425,
          "hizbQuarter": 196,
          "sajda": false
        },
        {
          "number": 4343,
          "text": "أَوَمَن يُنَشَّؤُا۟ فِى ٱلْحِلْيَةِ وَهُوَ فِى ٱلْخِصَامِ غَيْرُ مُبِينٍۢ",
          "numberInSurah": 18,
          "juz": 25,
          "manzil": 6,
          "page": 490,
          "ruku": 425,
          "hizbQuarter": 196,
          "sajda": false
        },
        {
          "number": 4344,
          "text": "وَجَعَلُوا۟ ٱلْمَلَٰٓئِكَةَ ٱلَّذِينَ هُمْ عِبَٰدُ ٱلرَّحْمَٰنِ إِنَٰثًا ۚ أَشَهِدُوا۟ خَلْقَهُمْ ۚ سَتُكْتَبُ شَهَٰدَتُهُمْ وَيُسْـَٔلُونَ",
          "numberInSurah": 19,
          "juz": 25,
          "manzil": 6,
          "page": 490,
          "ruku": 425,
          "hizbQuarter": 196,
          "sajda": false
        },
        {
          "number": 4345,
          "text": "وَقَالُوا۟ لَوْ شَآءَ ٱلرَّحْمَٰنُ مَا عَبَدْنَٰهُم ۗ مَّا لَهُم بِذَٰلِكَ مِنْ عِلْمٍ ۖ إِنْ هُمْ إِلَّا يَخْرُصُونَ",
          "numberInSurah": 20,
          "juz": 25,
          "manzil": 6,
          "page": 490,
          "ruku": 425,
          "hizbQuarter": 196,
          "sajda": false
        },
        {
          "number": 4346,
          "text": "أَمْ ءَاتَيْنَٰهُمْ كِتَٰبًۭا مِّن قَبْلِهِۦ فَهُم بِهِۦ مُسْتَمْسِكُونَ",
          "numberInSurah": 21,
          "juz": 25,
          "manzil": 6,
          "page": 490,
          "ruku": 425,
          "hizbQuarter": 196,
          "sajda": false
        },
        {
          "number": 4347,
          "text": "بَلْ قَالُوٓا۟ إِنَّا وَجَدْنَآ ءَابَآءَنَا عَلَىٰٓ أُمَّةٍۢ وَإِنَّا عَلَىٰٓ ءَاثَٰرِهِم مُّهْتَدُونَ",
          "numberInSurah": 22,
          "juz": 25,
          "manzil": 6,
          "page": 490,
          "ruku": 425,
          "hizbQuarter": 196,
          "sajda": false
        },
        {
          "number": 4348,
          "text": "وَكَذَٰلِكَ مَآ أَرْسَلْنَا مِن قَبْلِكَ فِى قَرْيَةٍۢ مِّن نَّذِيرٍ إِلَّا قَالَ مُتْرَفُوهَآ إِنَّا وَجَدْنَآ ءَابَآءَنَا عَلَىٰٓ أُمَّةٍۢ وَإِنَّا عَلَىٰٓ ءَاثَٰرِهِم مُّقْتَدُونَ",
          "numberInSurah": 23,
          "juz": 25,
          "manzil": 6,
          "page": 491,
          "ruku": 425,
          "hizbQuarter": 196,
          "sajda": false
        },
        {
          "number": 4349,
          "text": "۞ قَٰلَ أَوَلَوْ جِئْتُكُم بِأَهْدَىٰ مِمَّا وَجَدتُّمْ عَلَيْهِ ءَابَآءَكُمْ ۖ قَالُوٓا۟ إِنَّا بِمَآ أُرْسِلْتُم بِهِۦ كَٰفِرُونَ",
          "numberInSurah": 24,
          "juz": 25,
          "manzil": 6,
          "page": 491,
          "ruku": 425,
          "hizbQuarter": 197,
          "sajda": false
        },
        {
          "number": 4350,
          "text": "فَٱنتَقَمْنَا مِنْهُمْ ۖ فَٱنظُرْ كَيْفَ كَانَ عَٰقِبَةُ ٱلْمُكَذِّبِينَ",
          "numberInSurah": 25,
          "juz": 25,
          "manzil": 6,
          "page": 491,
          "ruku": 425,
          "hizbQuarter": 197,
          "sajda": false
        },
        {
          "number": 4351,
          "text": "وَإِذْ قَالَ إِبْرَٰهِيمُ لِأَبِيهِ وَقَوْمِهِۦٓ إِنَّنِى بَرَآءٌۭ مِّمَّا تَعْبُدُونَ",
          "numberInSurah": 26,
          "juz": 25,
          "manzil": 6,
          "page": 491,
          "ruku": 426,
          "hizbQuarter": 197,
          "sajda": false
        },
        {
          "number": 4352,
          "text": "إِلَّا ٱلَّذِى فَطَرَنِى فَإِنَّهُۥ سَيَهْدِينِ",
          "numberInSurah": 27,
          "juz": 25,
          "manzil": 6,
          "page": 491,
          "ruku": 426,
          "hizbQuarter": 197,
          "sajda": false
        },
        {
          "number": 4353,
          "text": "وَجَعَلَهَا كَلِمَةًۢ بَاقِيَةًۭ فِى عَقِبِهِۦ لَعَلَّهُمْ يَرْجِعُونَ",
          "numberInSurah": 28,
          "juz": 25,
          "manzil": 6,
          "page": 491,
          "ruku": 426,
          "hizbQuarter": 197,
          "sajda": false
        },
        {
          "number": 4354,
          "text": "بَلْ مَتَّعْتُ هَٰٓؤُلَآءِ وَءَابَآءَهُمْ حَتَّىٰ جَآءَهُمُ ٱلْحَقُّ وَرَسُولٌۭ مُّبِينٌۭ",
          "numberInSurah": 29,
          "juz": 25,
          "manzil": 6,
          "page": 491,
          "ruku": 426,
          "hizbQuarter": 197,
          "sajda": false
        },
        {
          "number": 4355,
          "text": "وَلَمَّا جَآءَهُمُ ٱلْحَقُّ قَالُوا۟ هَٰذَا سِحْرٌۭ وَإِنَّا بِهِۦ كَٰفِرُونَ",
          "numberInSurah": 30,
          "juz": 25,
          "manzil": 6,
          "page": 491,
          "ruku": 426,
          "hizbQuarter": 197,
          "sajda": false
        },
        {
          "number": 4356,
          "text": "وَقَالُوا۟ لَوْلَا نُزِّلَ هَٰذَا ٱلْقُرْءَانُ عَلَىٰ رَجُلٍۢ مِّنَ ٱلْقَرْيَتَيْنِ عَظِيمٍ",
          "numberInSurah": 31,
          "juz": 25,
          "manzil": 6,
          "page": 491,
          "ruku": 426,
          "hizbQuarter": 197,
          "sajda": false
        },
        {
          "number": 4357,
          "text": "أَهُمْ يَقْسِمُونَ رَحْمَتَ رَبِّكَ ۚ نَحْنُ قَسَمْنَا بَيْنَهُم مَّعِيشَتَهُمْ فِى ٱلْحَيَوٰةِ ٱلدُّنْيَا ۚ وَرَفَعْنَا بَعْضَهُمْ فَوْقَ بَعْضٍۢ دَرَجَٰتٍۢ لِّيَتَّخِذَ بَعْضُهُم بَعْضًۭا سُخْرِيًّۭا ۗ وَرَحْمَتُ رَبِّكَ خَيْرٌۭ مِّمَّا يَجْمَعُونَ",
          "numberInSurah": 32,
          "juz": 25,
          "manzil": 6,
          "page": 491,
          "ruku": 426,
          "hizbQuarter": 197,
          "sajda": false
        },
        {
          "number": 4358,
          "text": "وَلَوْلَآ أَن يَكُونَ ٱلنَّاسُ أُمَّةًۭ وَٰحِدَةًۭ لَّجَعَلْنَا لِمَن يَكْفُرُ بِٱلرَّحْمَٰنِ لِبُيُوتِهِمْ سُقُفًۭا مِّن فِضَّةٍۢ وَمَعَارِجَ عَلَيْهَا يَظْهَرُونَ",
          "numberInSurah": 33,
          "juz": 25,
          "manzil": 6,
          "page": 491,
          "ruku": 426,
          "hizbQuarter": 197,
          "sajda": false
        },
        {
          "number": 4359,
          "text": "وَلِبُيُوتِهِمْ أَبْوَٰبًۭا وَسُرُرًا عَلَيْهَا يَتَّكِـُٔونَ",
          "numberInSurah": 34,
          "juz": 25,
          "manzil": 6,
          "page": 492,
          "ruku": 426,
          "hizbQuarter": 197,
          "sajda": false
        },
        {
          "number": 4360,
          "text": "وَزُخْرُفًۭا ۚ وَإِن كُلُّ ذَٰلِكَ لَمَّا مَتَٰعُ ٱلْحَيَوٰةِ ٱلدُّنْيَا ۚ وَٱلْءَاخِرَةُ عِندَ رَبِّكَ لِلْمُتَّقِينَ",
          "numberInSurah": 35,
          "juz": 25,
          "manzil": 6,
          "page": 492,
          "ruku": 426,
          "hizbQuarter": 197,
          "sajda": false
        },
        {
          "number": 4361,
          "text": "وَمَن يَعْشُ عَن ذِكْرِ ٱلرَّحْمَٰنِ نُقَيِّضْ لَهُۥ شَيْطَٰنًۭا فَهُوَ لَهُۥ قَرِينٌۭ",
          "numberInSurah": 36,
          "juz": 25,
          "manzil": 6,
          "page": 492,
          "ruku": 427,
          "hizbQuarter": 197,
          "sajda": false
        },
        {
          "number": 4362,
          "text": "وَإِنَّهُمْ لَيَصُدُّونَهُمْ عَنِ ٱلسَّبِيلِ وَيَحْسَبُونَ أَنَّهُم مُّهْتَدُونَ",
          "numberInSurah": 37,
          "juz": 25,
          "manzil": 6,
          "page": 492,
          "ruku": 427,
          "hizbQuarter": 197,
          "sajda": false
        },
        {
          "number": 4363,
          "text": "حَتَّىٰٓ إِذَا جَآءَنَا قَالَ يَٰلَيْتَ بَيْنِى وَبَيْنَكَ بُعْدَ ٱلْمَشْرِقَيْنِ فَبِئْسَ ٱلْقَرِينُ",
          "numberInSurah": 38,
          "juz": 25,
          "manzil": 6,
          "page": 492,
          "ruku": 427,
          "hizbQuarter": 197,
          "sajda": false
        },
        {
          "number": 4364,
          "text": "وَلَن يَنفَعَكُمُ ٱلْيَوْمَ إِذ ظَّلَمْتُمْ أَنَّكُمْ فِى ٱلْعَذَابِ مُشْتَرِكُونَ",
          "numberInSurah": 39,
          "juz": 25,
          "manzil": 6,
          "page": 492,
          "ruku": 427,
          "hizbQuarter": 197,
          "sajda": false
        },
        {
          "number": 4365,
          "text": "أَفَأَنتَ تُسْمِعُ ٱلصُّمَّ أَوْ تَهْدِى ٱلْعُمْىَ وَمَن كَانَ فِى ضَلَٰلٍۢ مُّبِينٍۢ",
          "numberInSurah": 40,
          "juz": 25,
          "manzil": 6,
          "page": 492,
          "ruku": 427,
          "hizbQuarter": 197,
          "sajda": false
        },
        {
          "number": 4366,
          "text": "فَإِمَّا نَذْهَبَنَّ بِكَ فَإِنَّا مِنْهُم مُّنتَقِمُونَ",
          "numberInSurah": 41,
          "juz": 25,
          "manzil": 6,
          "page": 492,
          "ruku": 427,
          "hizbQuarter": 197,
          "sajda": false
        },
        {
          "number": 4367,
          "text": "أَوْ نُرِيَنَّكَ ٱلَّذِى وَعَدْنَٰهُمْ فَإِنَّا عَلَيْهِم مُّقْتَدِرُونَ",
          "numberInSurah": 42,
          "juz": 25,
          "manzil": 6,
          "page": 492,
          "ruku": 427,
          "hizbQuarter": 197,
          "sajda": false
        },
        {
          "number": 4368,
          "text": "فَٱسْتَمْسِكْ بِٱلَّذِىٓ أُوحِىَ إِلَيْكَ ۖ إِنَّكَ عَلَىٰ صِرَٰطٍۢ مُّسْتَقِيمٍۢ",
          "numberInSurah": 43,
          "juz": 25,
          "manzil": 6,
          "page": 492,
          "ruku": 427,
          "hizbQuarter": 197,
          "sajda": false
        },
        {
          "number": 4369,
          "text": "وَإِنَّهُۥ لَذِكْرٌۭ لَّكَ وَلِقَوْمِكَ ۖ وَسَوْفَ تُسْـَٔلُونَ",
          "numberInSurah": 44,
          "juz": 25,
          "manzil": 6,
          "page": 492,
          "ruku": 427,
          "hizbQuarter": 197,
          "sajda": false
        },
        {
          "number": 4370,
          "text": "وَسْـَٔلْ مَنْ أَرْسَلْنَا مِن قَبْلِكَ مِن رُّسُلِنَآ أَجَعَلْنَا مِن دُونِ ٱلرَّحْمَٰنِ ءَالِهَةًۭ يُعْبَدُونَ",
          "numberInSurah": 45,
          "juz": 25,
          "manzil": 6,
          "page": 492,
          "ruku": 427,
          "hizbQuarter": 197,
          "sajda": false
        },
        {
          "number": 4371,
          "text": "وَلَقَدْ أَرْسَلْنَا مُوسَىٰ بِـَٔايَٰتِنَآ إِلَىٰ فِرْعَوْنَ وَمَلَإِي۟هِۦ فَقَالَ إِنِّى رَسُولُ رَبِّ ٱلْعَٰلَمِينَ",
          "numberInSurah": 46,
          "juz": 25,
          "manzil": 6,
          "page": 492,
          "ruku": 428,
          "hizbQuarter": 197,
          "sajda": false
        },
        {
          "number": 4372,
          "text": "فَلَمَّا جَآءَهُم بِـَٔايَٰتِنَآ إِذَا هُم مِّنْهَا يَضْحَكُونَ",
          "numberInSurah": 47,
          "juz": 25,
          "manzil": 6,
          "page": 492,
          "ruku": 428,
          "hizbQuarter": 197,
          "sajda": false
        },
        {
          "number": 4373,
          "text": "وَمَا نُرِيهِم مِّنْ ءَايَةٍ إِلَّا هِىَ أَكْبَرُ مِنْ أُخْتِهَا ۖ وَأَخَذْنَٰهُم بِٱلْعَذَابِ لَعَلَّهُمْ يَرْجِعُونَ",
          "numberInSurah": 48,
          "juz": 25,
          "manzil": 6,
          "page": 493,
          "ruku": 428,
          "hizbQuarter": 197,
          "sajda": false
        },
        {
          "number": 4374,
          "text": "وَقَالُوا۟ يَٰٓأَيُّهَ ٱلسَّاحِرُ ٱدْعُ لَنَا رَبَّكَ بِمَا عَهِدَ عِندَكَ إِنَّنَا لَمُهْتَدُونَ",
          "numberInSurah": 49,
          "juz": 25,
          "manzil": 6,
          "page": 493,
          "ruku": 428,
          "hizbQuarter": 197,
          "sajda": false
        },
        {
          "number": 4375,
          "text": "فَلَمَّا كَشَفْنَا عَنْهُمُ ٱلْعَذَابَ إِذَا هُمْ يَنكُثُونَ",
          "numberInSurah": 50,
          "juz": 25,
          "manzil": 6,
          "page": 493,
          "ruku": 428,
          "hizbQuarter": 197,
          "sajda": false
        },
        {
          "number": 4376,
          "text": "وَنَادَىٰ فِرْعَوْنُ فِى قَوْمِهِۦ قَالَ يَٰقَوْمِ أَلَيْسَ لِى مُلْكُ مِصْرَ وَهَٰذِهِ ٱلْأَنْهَٰرُ تَجْرِى مِن تَحْتِىٓ ۖ أَفَلَا تُبْصِرُونَ",
          "numberInSurah": 51,
          "juz": 25,
          "manzil": 6,
          "page": 493,
          "ruku": 428,
          "hizbQuarter": 197,
          "sajda": false
        },
        {
          "number": 4377,
          "text": "أَمْ أَنَا۠ خَيْرٌۭ مِّنْ هَٰذَا ٱلَّذِى هُوَ مَهِينٌۭ وَلَا يَكَادُ يُبِينُ",
          "numberInSurah": 52,
          "juz": 25,
          "manzil": 6,
          "page": 493,
          "ruku": 428,
          "hizbQuarter": 197,
          "sajda": false
        },
        {
          "number": 4378,
          "text": "فَلَوْلَآ أُلْقِىَ عَلَيْهِ أَسْوِرَةٌۭ مِّن ذَهَبٍ أَوْ جَآءَ مَعَهُ ٱلْمَلَٰٓئِكَةُ مُقْتَرِنِينَ",
          "numberInSurah": 53,
          "juz": 25,
          "manzil": 6,
          "page": 493,
          "ruku": 428,
          "hizbQuarter": 197,
          "sajda": false
        },
        {
          "number": 4379,
          "text": "فَٱسْتَخَفَّ قَوْمَهُۥ فَأَطَاعُوهُ ۚ إِنَّهُمْ كَانُوا۟ قَوْمًۭا فَٰسِقِينَ",
          "numberInSurah": 54,
          "juz": 25,
          "manzil": 6,
          "page": 493,
          "ruku": 428,
          "hizbQuarter": 197,
          "sajda": false
        },
        {
          "number": 4380,
          "text": "فَلَمَّآ ءَاسَفُونَا ٱنتَقَمْنَا مِنْهُمْ فَأَغْرَقْنَٰهُمْ أَجْمَعِينَ",
          "numberInSurah": 55,
          "juz": 25,
          "manzil": 6,
          "page": 493,
          "ruku": 428,
          "hizbQuarter": 197,
          "sajda": false
        },
        {
          "number": 4381,
          "text": "فَجَعَلْنَٰهُمْ سَلَفًۭا وَمَثَلًۭا لِّلْءَاخِرِينَ",
          "numberInSurah": 56,
          "juz": 25,
          "manzil": 6,
          "page": 493,
          "ruku": 428,
          "hizbQuarter": 197,
          "sajda": false
        },
        {
          "number": 4382,
          "text": "۞ وَلَمَّا ضُرِبَ ٱبْنُ مَرْيَمَ مَثَلًا إِذَا قَوْمُكَ مِنْهُ يَصِدُّونَ",
          "numberInSurah": 57,
          "juz": 25,
          "manzil": 6,
          "page": 493,
          "ruku": 429,
          "hizbQuarter": 198,
          "sajda": false
        },
        {
          "number": 4383,
          "text": "وَقَالُوٓا۟ ءَأَٰلِهَتُنَا خَيْرٌ أَمْ هُوَ ۚ مَا ضَرَبُوهُ لَكَ إِلَّا جَدَلًۢا ۚ بَلْ هُمْ قَوْمٌ خَصِمُونَ",
          "numberInSurah": 58,
          "juz": 25,
          "manzil": 6,
          "page": 493,
          "ruku": 429,
          "hizbQuarter": 198,
          "sajda": false
        },
        {
          "number": 4384,
          "text": "إِنْ هُوَ إِلَّا عَبْدٌ أَنْعَمْنَا عَلَيْهِ وَجَعَلْنَٰهُ مَثَلًۭا لِّبَنِىٓ إِسْرَٰٓءِيلَ",
          "numberInSurah": 59,
          "juz": 25,
          "manzil": 6,
          "page": 493,
          "ruku": 429,
          "hizbQuarter": 198,
          "sajda": false
        },
        {
          "number": 4385,
          "text": "وَلَوْ نَشَآءُ لَجَعَلْنَا مِنكُم مَّلَٰٓئِكَةًۭ فِى ٱلْأَرْضِ يَخْلُفُونَ",
          "numberInSurah": 60,
          "juz": 25,
          "manzil": 6,
          "page": 493,
          "ruku": 429,
          "hizbQuarter": 198,
          "sajda": false
        },
        {
          "number": 4386,
          "text": "وَإِنَّهُۥ لَعِلْمٌۭ لِّلسَّاعَةِ فَلَا تَمْتَرُنَّ بِهَا وَٱتَّبِعُونِ ۚ هَٰذَا صِرَٰطٌۭ مُّسْتَقِيمٌۭ",
          "numberInSurah": 61,
          "juz": 25,
          "manzil": 6,
          "page": 494,
          "ruku": 429,
          "hizbQuarter": 198,
          "sajda": false
        },
        {
          "number": 4387,
          "text": "وَلَا يَصُدَّنَّكُمُ ٱلشَّيْطَٰنُ ۖ إِنَّهُۥ لَكُمْ عَدُوٌّۭ مُّبِينٌۭ",
          "numberInSurah": 62,
          "juz": 25,
          "manzil": 6,
          "page": 494,
          "ruku": 429,
          "hizbQuarter": 198,
          "sajda": false
        },
        {
          "number": 4388,
          "text": "وَلَمَّا جَآءَ عِيسَىٰ بِٱلْبَيِّنَٰتِ قَالَ قَدْ جِئْتُكُم بِٱلْحِكْمَةِ وَلِأُبَيِّنَ لَكُم بَعْضَ ٱلَّذِى تَخْتَلِفُونَ فِيهِ ۖ فَٱتَّقُوا۟ ٱللَّهَ وَأَطِيعُونِ",
          "numberInSurah": 63,
          "juz": 25,
          "manzil": 6,
          "page": 494,
          "ruku": 429,
          "hizbQuarter": 198,
          "sajda": false
        },
        {
          "number": 4389,
          "text": "إِنَّ ٱللَّهَ هُوَ رَبِّى وَرَبُّكُمْ فَٱعْبُدُوهُ ۚ هَٰذَا صِرَٰطٌۭ مُّسْتَقِيمٌۭ",
          "numberInSurah": 64,
          "juz": 25,
          "manzil": 6,
          "page": 494,
          "ruku": 429,
          "hizbQuarter": 198,
          "sajda": false
        },
        {
          "number": 4390,
          "text": "فَٱخْتَلَفَ ٱلْأَحْزَابُ مِنۢ بَيْنِهِمْ ۖ فَوَيْلٌۭ لِّلَّذِينَ ظَلَمُوا۟ مِنْ عَذَابِ يَوْمٍ أَلِيمٍ",
          "numberInSurah": 65,
          "juz": 25,
          "manzil": 6,
          "page": 494,
          "ruku": 429,
          "hizbQuarter": 198,
          "sajda": false
        },
        {
          "number": 4391,
          "text": "هَلْ يَنظُرُونَ إِلَّا ٱلسَّاعَةَ أَن تَأْتِيَهُم بَغْتَةًۭ وَهُمْ لَا يَشْعُرُونَ",
          "numberInSurah": 66,
          "juz": 25,
          "manzil": 6,
          "page": 494,
          "ruku": 429,
          "hizbQuarter": 198,
          "sajda": false
        },
        {
          "number": 4392,
          "text": "ٱلْأَخِلَّآءُ يَوْمَئِذٍۭ بَعْضُهُمْ لِبَعْضٍ عَدُوٌّ إِلَّا ٱلْمُتَّقِينَ",
          "numberInSurah": 67,
          "juz": 25,
          "manzil": 6,
          "page": 494,
          "ruku": 429,
          "hizbQuarter": 198,
          "sajda": false
        },
        {
          "number": 4393,
          "text": "يَٰعِبَادِ لَا خَوْفٌ عَلَيْكُمُ ٱلْيَوْمَ وَلَآ أَنتُمْ تَحْزَنُونَ",
          "numberInSurah": 68,
          "juz": 25,
          "manzil": 6,
          "page": 494,
          "ruku": 430,
          "hizbQuarter": 198,
          "sajda": false
        },
        {
          "number": 4394,
          "text": "ٱلَّذِينَ ءَامَنُوا۟ بِـَٔايَٰتِنَا وَكَانُوا۟ مُسْلِمِينَ",
          "numberInSurah": 69,
          "juz": 25,
          "manzil": 6,
          "page": 494,
          "ruku": 430,
          "hizbQuarter": 198,
          "sajda": false
        },
        {
          "number": 4395,
          "text": "ٱدْخُلُوا۟ ٱلْجَنَّةَ أَنتُمْ وَأَزْوَٰجُكُمْ تُحْبَرُونَ",
          "numberInSurah": 70,
          "juz": 25,
          "manzil": 6,
          "page": 494,
          "ruku": 430,
          "hizbQuarter": 198,
          "sajda": false
        },
        {
          "number": 4396,
          "text": "يُطَافُ عَلَيْهِم بِصِحَافٍۢ مِّن ذَهَبٍۢ وَأَكْوَابٍۢ ۖ وَفِيهَا مَا تَشْتَهِيهِ ٱلْأَنفُسُ وَتَلَذُّ ٱلْأَعْيُنُ ۖ وَأَنتُمْ فِيهَا خَٰلِدُونَ",
          "numberInSurah": 71,
          "juz": 25,
          "manzil": 6,
          "page": 494,
          "ruku": 430,
          "hizbQuarter": 198,
          "sajda": false
        },
        {
          "number": 4397,
          "text": "وَتِلْكَ ٱلْجَنَّةُ ٱلَّتِىٓ أُورِثْتُمُوهَا بِمَا كُنتُمْ تَعْمَلُونَ",
          "numberInSurah": 72,
          "juz": 25,
          "manzil": 6,
          "page": 494,
          "ruku": 430,
          "hizbQuarter": 198,
          "sajda": false
        },
        {
          "number": 4398,
          "text": "لَكُمْ فِيهَا فَٰكِهَةٌۭ كَثِيرَةٌۭ مِّنْهَا تَأْكُلُونَ",
          "numberInSurah": 73,
          "juz": 25,
          "manzil": 6,
          "page": 494,
          "ruku": 430,
          "hizbQuarter": 198,
          "sajda": false
        },
        {
          "number": 4399,
          "text": "إِنَّ ٱلْمُجْرِمِينَ فِى عَذَابِ جَهَنَّمَ خَٰلِدُونَ",
          "numberInSurah": 74,
          "juz": 25,
          "manzil": 6,
          "page": 495,
          "ruku": 430,
          "hizbQuarter": 198,
          "sajda": false
        },
        {
          "number": 4400,
          "text": "لَا يُفَتَّرُ عَنْهُمْ وَهُمْ فِيهِ مُبْلِسُونَ",
          "numberInSurah": 75,
          "juz": 25,
          "manzil": 6,
          "page": 495,
          "ruku": 430,
          "hizbQuarter": 198,
          "sajda": false
        },
        {
          "number": 4401,
          "text": "وَمَا ظَلَمْنَٰهُمْ وَلَٰكِن كَانُوا۟ هُمُ ٱلظَّٰلِمِينَ",
          "numberInSurah": 76,
          "juz": 25,
          "manzil": 6,
          "page": 495,
          "ruku": 430,
          "hizbQuarter": 198,
          "sajda": false
        },
        {
          "number": 4402,
          "text": "وَنَادَوْا۟ يَٰمَٰلِكُ لِيَقْضِ عَلَيْنَا رَبُّكَ ۖ قَالَ إِنَّكُم مَّٰكِثُونَ",
          "numberInSurah": 77,
          "juz": 25,
          "manzil": 6,
          "page": 495,
          "ruku": 430,
          "hizbQuarter": 198,
          "sajda": false
        },
        {
          "number": 4403,
          "text": "لَقَدْ جِئْنَٰكُم بِٱلْحَقِّ وَلَٰكِنَّ أَكْثَرَكُمْ لِلْحَقِّ كَٰرِهُونَ",
          "numberInSurah": 78,
          "juz": 25,
          "manzil": 6,
          "page": 495,
          "ruku": 430,
          "hizbQuarter": 198,
          "sajda": false
        },
        {
          "number": 4404,
          "text": "أَمْ أَبْرَمُوٓا۟ أَمْرًۭا فَإِنَّا مُبْرِمُونَ",
          "numberInSurah": 79,
          "juz": 25,
          "manzil": 6,
          "page": 495,
          "ruku": 430,
          "hizbQuarter": 198,
          "sajda": false
        },
        {
          "number": 4405,
          "text": "أَمْ يَحْسَبُونَ أَنَّا لَا نَسْمَعُ سِرَّهُمْ وَنَجْوَىٰهُم ۚ بَلَىٰ وَرُسُلُنَا لَدَيْهِمْ يَكْتُبُونَ",
          "numberInSurah": 80,
          "juz": 25,
          "manzil": 6,
          "page": 495,
          "ruku": 430,
          "hizbQuarter": 198,
          "sajda": false
        },
        {
          "number": 4406,
          "text": "قُلْ إِن كَانَ لِلرَّحْمَٰنِ وَلَدٌۭ فَأَنَا۠ أَوَّلُ ٱلْعَٰبِدِينَ",
          "numberInSurah": 81,
          "juz": 25,
          "manzil": 6,
          "page": 495,
          "ruku": 430,
          "hizbQuarter": 198,
          "sajda": false
        },
        {
          "number": 4407,
          "text": "سُبْحَٰنَ رَبِّ ٱلسَّمَٰوَٰتِ وَٱلْأَرْضِ رَبِّ ٱلْعَرْشِ عَمَّا يَصِفُونَ",
          "numberInSurah": 82,
          "juz": 25,
          "manzil": 6,
          "page": 495,
          "ruku": 430,
          "hizbQuarter": 198,
          "sajda": false
        },
        {
          "number": 4408,
          "text": "فَذَرْهُمْ يَخُوضُوا۟ وَيَلْعَبُوا۟ حَتَّىٰ يُلَٰقُوا۟ يَوْمَهُمُ ٱلَّذِى يُوعَدُونَ",
          "numberInSurah": 83,
          "juz": 25,
          "manzil": 6,
          "page": 495,
          "ruku": 430,
          "hizbQuarter": 198,
          "sajda": false
        },
        {
          "number": 4409,
          "text": "وَهُوَ ٱلَّذِى فِى ٱلسَّمَآءِ إِلَٰهٌۭ وَفِى ٱلْأَرْضِ إِلَٰهٌۭ ۚ وَهُوَ ٱلْحَكِيمُ ٱلْعَلِيمُ",
          "numberInSurah": 84,
          "juz": 25,
          "manzil": 6,
          "page": 495,
          "ruku": 430,
          "hizbQuarter": 198,
          "sajda": false
        },
        {
          "number": 4410,
          "text": "وَتَبَارَكَ ٱلَّذِى لَهُۥ مُلْكُ ٱلسَّمَٰوَٰتِ وَٱلْأَرْضِ وَمَا بَيْنَهُمَا وَعِندَهُۥ عِلْمُ ٱلسَّاعَةِ وَإِلَيْهِ تُرْجَعُونَ",
          "numberInSurah": 85,
          "juz": 25,
          "manzil": 6,
          "page": 495,
          "ruku": 430,
          "hizbQuarter": 198,
          "sajda": false
        },
        {
          "number": 4411,
          "text": "وَلَا يَمْلِكُ ٱلَّذِينَ يَدْعُونَ مِن دُونِهِ ٱلشَّفَٰعَةَ إِلَّا مَن شَهِدَ بِٱلْحَقِّ وَهُمْ يَعْلَمُونَ",
          "numberInSurah": 86,
          "juz": 25,
          "manzil": 6,
          "page": 495,
          "ruku": 430,
          "hizbQuarter": 198,
          "sajda": false
        },
        {
          "number": 4412,
          "text": "وَلَئِن سَأَلْتَهُم مَّنْ خَلَقَهُمْ لَيَقُولُنَّ ٱللَّهُ ۖ فَأَنَّىٰ يُؤْفَكُونَ",
          "numberInSurah": 87,
          "juz": 25,
          "manzil": 6,
          "page": 495,
          "ruku": 430,
          "hizbQuarter": 198,
          "sajda": false
        },
        {
          "number": 4413,
          "text": "وَقِيلِهِۦ يَٰرَبِّ إِنَّ هَٰٓؤُلَآءِ قَوْمٌۭ لَّا يُؤْمِنُونَ",
          "numberInSurah": 88,
          "juz": 25,
          "manzil": 6,
          "page": 495,
          "ruku": 430,
          "hizbQuarter": 198,
          "sajda": false
        },
        {
          "number": 4414,
          "text": "فَٱصْفَحْ عَنْهُمْ وَقُلْ سَلَٰمٌۭ ۚ فَسَوْفَ يَعْلَمُونَ",
          "numberInSurah": 89,
          "juz": 25,
          "manzil": 6,
          "page": 495,
          "ruku": 430,
          "hizbQuarter": 198,
          "sajda": false
        }
      ],
      "edition": {
        "identifier": "quran-uthmani",
        "language": "ar",
        "name": "Uthamani",
        "englishName": "Uthamani",
        "format": "text",
        "type": "quran"
      }
    }
  ]
}